nezuki/__init__.py
nezuki/Browser/Browser.py
nezuki/Browser/__init__.py
nezuki/Database/Database.py
nezuki/Database/__init__.py
nezuki/Decorators/__init__.py
nezuki/Decorators/deprecated.py
nezuki/Decorators/experimental.py
nezuki/Decorators/legacy.py
nezuki/EncoderDecoder/EncoderDecoder.py
nezuki/EncoderDecoder/__init__.py
nezuki/EncoderDecoder/aesManager.py
nezuki/EncoderDecoder/hashGenerator.py
nezuki/EncoderDecoder/qrCode.py
nezuki/Http/Http.py
nezuki/Http/__init__.py
nezuki/JsonManager/JsonManager.py
nezuki/JsonManager/__init__.py
nezuki/Logger/Logger.py
nezuki/Logger/Logger_2.py
nezuki/Logger/__init__.py
nezuki/Mail/Mail.py
nezuki/Mail/__init__.py
nezuki/Parser/Cedolini.py
nezuki/Parser/YAML.py
nezuki/Parser/__init__.py
nezuki/ServerUtils/ServerUtils.py
nezuki/ServerUtils/__init__.py
nezuki/StreamingParser/AnimeSaturn.py
nezuki/StreamingParser/JWPlayer.py
nezuki/StreamingParser/StreamingCommunity.py
nezuki/StreamingParser/__init__.py
nezuki/StreamingParser/test.py
nezuki/TMDB/Configurations.py
nezuki/TMDB/Genres.py
nezuki/TMDB/Networks.py
nezuki/TMDB/Search.py
nezuki/TMDB/TMDB.py
nezuki/TMDB/TV.py
nezuki/TMDB/TVEpisodes.py
nezuki/TMDB/TVSeasons.py
nezuki/TMDB/__init__.py
nezuki/TMDB/test.py
nezuki/YamlManager/YamlManager.py
nezuki/YamlManager/__init__.py
nezuki-2.2.0.dist-info/licenses/LICENSE
nezuki-2.2.0.dist-info/METADATA
nezuki-2.2.0.dist-info/WHEEL
nezuki-2.2.0.dist-info/entry_points.txt
nezuki-2.2.0.dist-info/top_level.txt
nezuki-2.2.0.dist-info/RECORD
