Metadata-Version: 2.4
Name: nezuki
Version: 2.2.0
Summary: Un pacchetto per la gestione della domotica e servizi server
Home-page: https://github.com/KingKaitoKid/Nezuki
Author: Sergio Catacci
Author-email: sergio.catacci@icloud.com
Project-URL: Bug Reports, https://github.com/KingKaitoKid/Nezuki/issues
Project-URL: Source, https://github.com/KingKaitoKid/Nezuki
Keywords: nezuki domotica home-server
Classifier: Programming Language :: Python :: 3
Classifier: License :: OSI Approved :: MIT License
Classifier: Operating System :: OS Independent
Requires-Python: >=3.12
License-File: LICENSE
Requires-Dist: aiohappyeyeballs==2.6.1
Requires-Dist: aiohttp==3.12.15
Requires-Dist: aiosignal==1.4.0
Requires-Dist: annotated-types==0.7.0
Requires-Dist: anyio==4.10.0
Requires-Dist: asyncpg==0.30.0
Requires-Dist: attrs==25.3.0
Requires-Dist: blinker==1.9.0
Requires-Dist: certifi==2025.8.3
Requires-Dist: cffi==1.17.1
Requires-Dist: charset-normalizer==3.4.3
Requires-Dist: click==8.2.1
Requires-Dist: cloudflare==4.3.1
Requires-Dist: colorama==0.4.6
Requires-Dist: coloredlogs==15.0.1
Requires-Dist: cryptography==45.0.6
Requires-Dist: distro==1.9.0
Requires-Dist: docutils==0.22
Requires-Dist: Flask==3.1.1
Requires-Dist: flask-cors==6.0.1
Requires-Dist: frozenlist==1.7.0
Requires-Dist: h11==0.16.0
Requires-Dist: httpcore==1.0.9
Requires-Dist: httpx==0.28.1
Requires-Dist: humanfriendly==10.0
Requires-Dist: id==1.5.0
Requires-Dist: idna==3.10
Requires-Dist: itsdangerous==2.2.0
Requires-Dist: jaraco.classes==3.4.0
Requires-Dist: jaraco.context==6.0.1
Requires-Dist: jaraco.functools==4.2.1
Requires-Dist: jeepney==0.9.0
Requires-Dist: Jinja2==3.1.6
Requires-Dist: jsonpath-ng==1.7.0
Requires-Dist: keyring==25.6.0
Requires-Dist: markdown-it-py==4.0.0
Requires-Dist: MarkupSafe==3.0.2
Requires-Dist: mdurl==0.1.2
Requires-Dist: more-itertools==10.7.0
Requires-Dist: multidict==6.6.4
Requires-Dist: mysql-connector-python==9.4.0
Requires-Dist: nezuki>=2.0.15
Requires-Dist: nh3==0.3.0
Requires-Dist: outcome==1.3.0.post0
Requires-Dist: packaging==25.0
Requires-Dist: pillow==11.3.0
Requires-Dist: ply==3.11
Requires-Dist: propcache==0.3.2
Requires-Dist: psycopg==3.2.9
Requires-Dist: psycopg-binary==3.2.9
Requires-Dist: psycopg-pool==3.2.6
Requires-Dist: pycparser==2.22
Requires-Dist: pydantic==2.11.7
Requires-Dist: pydantic_core==2.33.2
Requires-Dist: pyflakes==3.4.0
Requires-Dist: Pygments==2.19.2
Requires-Dist: PySocks==1.7.1
Requires-Dist: PyYAML==6.0.2
Requires-Dist: qrcode==8.2
Requires-Dist: readme_renderer==44.0
Requires-Dist: requests==2.32.4
Requires-Dist: requests-toolbelt==1.0.0
Requires-Dist: rfc3986==2.0.0
Requires-Dist: rich==14.1.0
Requires-Dist: SecretStorage==3.3.3
Requires-Dist: selenium==4.35.0
Requires-Dist: setuptools==80.9.0
Requires-Dist: sniffio==1.3.1
Requires-Dist: sortedcontainers==2.4.0
Requires-Dist: trio==0.30.0
Requires-Dist: trio-websocket==0.12.2
Requires-Dist: twine==6.1.0
Requires-Dist: typing-inspection==0.4.1
Requires-Dist: typing_extensions==4.14.1
Requires-Dist: urllib3==2.5.0
Requires-Dist: websocket-client==1.8.0
Requires-Dist: Werkzeug==3.1.3
Requires-Dist: wheel==0.45.1
Requires-Dist: wsproto==1.2.0
Requires-Dist: yarl==1.20.1
Requires-Dist: uvicorn>=0.37.0
Dynamic: author
Dynamic: author-email
Dynamic: classifier
Dynamic: description
Dynamic: description-content-type
Dynamic: home-page
Dynamic: keywords
Dynamic: license-file
Dynamic: project-url
Dynamic: requires-dist
Dynamic: requires-python
Dynamic: summary
